{
  "appPageId" : "fda4a77f-2276-4705-b558-32e83150e06c",
  "componentName" : "siteforce:sldsOneColLayout",
  "id" : "0e790a38-86c3-4f92-ae06-6bd5ff1a6eaf",
  "label" : "User Settings",
  "regions" : [ {
    "id" : "4a60de46-c4e1-4e6d-a114-06d7d8207506",
    "regionName" : "header",
    "type" : "region"
  }, {
    "components" : [ {
      "componentAttributes" : {
        "accountSectionTitle" : "Account",
        "accountTabName" : "Account Management",
        "connectedSourcesTabName" : "Connected Sources",
        "deleteAccountButtonTitle" : "Deactivate My Account",
        "deleteAccountConfirmationPopupBody" : "After you deactivate your account, you'll lose access to this site.",
        "deleteAccountConfirmationPopupButtonTitle" : "Got It",
        "deleteAccountConfirmationPopupTitle" : "Deactivate your account?",
        "deleteAccountErrorMessage" : "Something went wrong. Contact your site administrator.",
        "deleteAccountSectionTitle" : "Deactivate Account",
        "emailNotificationsTitle" : "Email Notifications",
        "emailSectionDescText" : "When email notifications are enabled, email me when someone:",
        "hideAccountDeleteSection" : true,
        "hideChatterNotificationSettings" : true,
        "hideConnectedSources" : false,
        "hideEmailNotificationSettings" : false,
        "hideProfileVisibilitySettings" : true,
        "id" : "{!recordId}",
        "locationTitle" : "Location",
        "profileSectionDescText" : "Customize who is able to see what on your profile page",
        "profileSectionToolTipText" : "Restricted: Visible to the employees of the company that created the site. Members: Visible to logged-in members. Public: Visible to anyone viewing pages that don't require login.",
        "profileVisibilityTitle" : "Profile Visibility",
        "settingsPageTitle" : "My Settings"
      },
      "componentName" : "forceCommunity:userSettingsCustomizable",
      "id" : "98de2c84-e187-4d45-8af1-8eb5b09d9e89",
      "renderPriority" : "NEUTRAL",
      "renditionMap" : { },
      "type" : "component"
    } ],
    "id" : "967887ce-a294-4b6b-a13b-4ed235ac1978",
    "regionName" : "content",
    "type" : "region"
  }, {
    "id" : "e7eea981-e3a0-44d0-b882-c5b33b58666e",
    "regionName" : "footer",
    "type" : "region"
  } ],
  "themeLayoutType" : "Inner",
  "type" : "view",
  "viewType" : "usersettings"
}